hypersphereapi/__init__.py
hypersphereapi/sdk.py
hypersphereapi-1.0.0.dist-info/METADATA
hypersphereapi-1.0.0.dist-info/WHEEL
hypersphereapi-1.0.0.dist-info/licenses/LICENSE
hypersphereapi-1.0.0.dist-info/RECORD
