Metadata-Version: 2.1
Name: hypersphereapi
Version: 1.0.0
Summary: Use HyperSphere's Python API to rapidly secure your data in a quantum-immune fashion!
Project-URL: Homepage, https://hyperspheretech.com
Project-URL: Documentation, https://docs.hyperspheretech.com
Author-email: Gregory Morford <gregory.morford@hyperspheretech.com>
License-File: LICENSE
Classifier: License :: OSI Approved :: MIT License
Classifier: Operating System :: OS Independent
Classifier: Programming Language :: Python :: 3
Requires-Python: >=3.7
